setup.py
amitu/__init__.py
amitu/putils/__init__.py
amitu/putils/mysql.py
amitu/putils/stack.py
amitu_putils.egg-info/PKG-INFO
amitu_putils.egg-info/SOURCES.txt
amitu_putils.egg-info/dependency_links.txt
amitu_putils.egg-info/namespace_packages.txt
amitu_putils.egg-info/top_level.txt
amitu_putils.egg-info/zip-safe