Metadata-Version: 1.0
Name: amitu-putils
Version: 0.1.0
Summary: Python Utilities
Home-page: http://github.com/amitu/amitu-putils/
Author: Amit Upadhyay
Author-email: upadhyay@gmail.com
License: BSD
Platform: UNKNOWN
